cliar/__init__.py
cliar/cliar.py
cliar/utils.py
cliar-1.3.3.dist-info/WHEEL
cliar-1.3.3.dist-info/METADATA
cliar-1.3.3.dist-info/RECORD
