Metadata-Version: 2.1
Name: cliar
Version: 1.3.3
Summary: Create CLIs with classes and type hints.
Home-page: https://moigagoo.github.io/cliar/
License: MIT
Keywords: cli,commandline
Author: Constantine Molchanov
Author-email: moigagoo@live.com
Requires-Python: >=3.6,<4.0
Classifier: License :: OSI Approved :: MIT License
Classifier: Programming Language :: Python :: 3
Classifier: Programming Language :: Python :: 3.6
Classifier: Programming Language :: Python :: 3.7
Classifier: Programming Language :: Python :: 3.8
Project-URL: Documentation, https://moigagoo.github.io/cliar/
Project-URL: Repository, https://github.com/moigagoo/cliar/
